find_github_email/__init__.py
find_github_email/main.py
find_github_email-1.2.6.dist-info/LICENSE
find_github_email-1.2.6.dist-info/METADATA
find_github_email-1.2.6.dist-info/WHEEL
find_github_email-1.2.6.dist-info/top_level.txt
find_github_email-1.2.6.dist-info/RECORD
