Metadata-Version: 2.1
Name: find-github-email
Version: 1.2.6
Summary: Find any GitHub user’s email address
Home-page: https://github.com/UdhavPawar/find_github_email
Author: Udhav Pawar
Author-email: upawar78@gmail.com
License: MIT
Download-URL: https://github.com/UdhavPawar/find_github_email/archive/v1.0.tar.gz
Keywords: github-profile,github-email,python3,github-api,github,email,pypi,pypi-package
Platform: UNKNOWN
License-File: LICENSE
Requires-Dist: requests
